Makefile
README.txt
setup.cfg
setup.py
docs/HISTORY.txt
zopyx/__init__.py
zopyx.sharepoint.egg-info/PKG-INFO
zopyx.sharepoint.egg-info/SOURCES.txt
zopyx.sharepoint.egg-info/dependency_links.txt
zopyx.sharepoint.egg-info/entry_points.txt
zopyx.sharepoint.egg-info/namespace_packages.txt
zopyx.sharepoint.egg-info/not-zip-safe
zopyx.sharepoint.egg-info/requires.txt
zopyx.sharepoint.egg-info/top_level.txt
zopyx/sharepoint/__init__.py
zopyx/sharepoint/cli.py
zopyx/sharepoint/connector.py
zopyx/sharepoint/example.py
zopyx/sharepoint/logger.py
zopyx/sharepoint/patches.py
zopyx/sharepoint/tests/__init__.py
zopyx/sharepoint/tests/test_connector.py