Metadata-Version: 1.0
Name: zopyx.sharepoint
Version: 0.2.0
Summary: Experimental Python-Sharepoint connector
Home-page: http://pypi.python.org/pypi/zopyx.sharepoint
Author: Andreas Jung
Author-email: info@zopyx.com
License: ZPL
Keywords: Sharepoint
Platform: UNKNOWN
Classifier: Programming Language :: Python
Classifier: Topic :: Software Development :: Libraries :: Python Modules
